repo_cli/.DS_Store
repo_cli/Maverick/Builder.py
repo_cli/Maverick/Cache.py
repo_cli/Maverick/Config.py
repo_cli/Maverick/Content.py
repo_cli/Maverick/Galileo/.DS_Store
repo_cli/Maverick/Galileo/LICENSE
repo_cli/Maverick/Galileo/README.md
repo_cli/Maverick/Galileo/__init__.py
repo_cli/Maverick/Galileo/assets/ExSearch/ExSearch-182e5a8868.css
repo_cli/Maverick/Galileo/assets/ExSearch/ExSearch-493cb9cd89.js
repo_cli/Maverick/Galileo/assets/ExSearch/iconfont.eot
repo_cli/Maverick/Galileo/assets/ExSearch/iconfont.svg
repo_cli/Maverick/Galileo/assets/ExSearch/iconfont.ttf
repo_cli/Maverick/Galileo/assets/ExSearch/iconfont.woff
repo_cli/Maverick/Galileo/assets/ExSearch/iconfont.woff2
repo_cli/Maverick/Galileo/assets/ExSearch/jquery.min.js
repo_cli/Maverick/Galileo/assets/auto-render.min.js
repo_cli/Maverick/Galileo/assets/fonts/KaTeX_AMS-Regular.ttf
repo_cli/Maverick/Galileo/assets/fonts/KaTeX_AMS-Regular.woff
repo_cli/Maverick/Galileo/assets/fonts/KaTeX_AMS-Regular.woff2
repo_cli/Maverick/Galileo/assets/fonts/KaTeX_Caligraphic-Bold.ttf
repo_cli/Maverick/Galileo/assets/fonts/KaTeX_Caligraphic-Bold.woff
repo_cli/Maverick/Galileo/assets/fonts/KaTeX_Caligraphic-Bold.woff2
repo_cli/Maverick/Galileo/assets/fonts/KaTeX_Caligraphic-Regular.ttf
repo_cli/Maverick/Galileo/assets/fonts/KaTeX_Caligraphic-Regular.woff
repo_cli/Maverick/Galileo/assets/fonts/KaTeX_Caligraphic-Regular.woff2
repo_cli/Maverick/Galileo/assets/fonts/KaTeX_Fraktur-Bold.ttf
repo_cli/Maverick/Galileo/assets/fonts/KaTeX_Fraktur-Bold.woff
repo_cli/Maverick/Galileo/assets/fonts/KaTeX_Fraktur-Bold.woff2
repo_cli/Maverick/Galileo/assets/fonts/KaTeX_Fraktur-Regular.ttf
repo_cli/Maverick/Galileo/assets/fonts/KaTeX_Fraktur-Regular.woff
repo_cli/Maverick/Galileo/assets/fonts/KaTeX_Fraktur-Regular.woff2
repo_cli/Maverick/Galileo/assets/fonts/KaTeX_Main-Bold.ttf
repo_cli/Maverick/Galileo/assets/fonts/KaTeX_Main-Bold.woff
repo_cli/Maverick/Galileo/assets/fonts/KaTeX_Main-Bold.woff2
repo_cli-0.0.1.14.dist-info/entry_points.txt
repo_cli-0.0.1.14.dist-info/LICENSE
repo_cli-0.0.1.14.dist-info/WHEEL
repo_cli-0.0.1.14.dist-info/METADATA
repo_cli-0.0.1.14.dist-info/RECORD
